<?xml version="1.0" encoding="utf-8" ?>
<configuration>
	<keycodes>
		<keycode virtualKeyCode="0"  canOn="false" canOff="false" shortcut="none">
			<names>
				<name value="None" />
			</names>
		</keycode>
		<keycode virtualKeyCode="1"  canOn="false" canOff="false" shortcut="none">
			<names>
				<name value="LButton" />
			</names>
		</keycode>
		<keycode virtualKeyCode="2"  canOn="false" canOff="false" shortcut="none">
			<names>
				<name value="RButton" />
			</names>
		</keycode>
		<keycode virtualKeyCode="3"  canOn="false" canOff="false" shortcut="none">
			<names>
				<name value="Cancel" />
			</names>
		</keycode>
		<keycode virtualKeyCode="4"  canOn="false" canOff="false" shortcut="none">
			<names>
				<name value="MButton" />
			</names>
		</keycode>
		<keycode virtualKeyCode="5"  canOn="false" canOff="false" shortcut="none">
			<names>
				<name value="XButton1" />
			</names>
		</keycode>
		<keycode virtualKeyCode="6"  canOn="false" canOff="false" shortcut="none">
			<names>
				<name value="XButton2" />
			</names>
		</keycode>
		<keycode virtualKeyCode="8"  canOn="false" canOff="false" shortcut="none">
			<names>
				<name value="Back" />
			</names>
		</keycode>
		<keycode virtualKeyCode="9"  canOn="false" canOff="false" shortcut="none">
			<names>
				<name value="Tab" />
			</names>
		</keycode>
		<keycode virtualKeyCode="10"  canOn="false" canOff="false" shortcut="none">
			<names>
				<name value="LineFeed" />
			</names>
		</keycode>
		<keycode virtualKeyCode="12"  canOn="false" canOff="false" shortcut="none">
			<names>
				<name value="Clear" />
			</names>
		</keycode>
		<keycode virtualKeyCode="13"  canOn="false" canOff="false" shortcut="none">
			<names>
				<name value="Enter" />
				<name value="Return" />
			</names>
		</keycode>
		<keycode virtualKeyCode="16"  canOn="false" canOff="false" shortcut="none">
			<names>
				<name value="ShiftKey" />
			</names>
		</keycode>
		<keycode virtualKeyCode="17"  canOn="false" canOff="false" shortcut="none">
			<names>
				<name value="ControlKey" />
			</names>
		</keycode>
		<keycode virtualKeyCode="18"  canOn="false" canOff="false" shortcut="none">
			<names>
				<name value="Menu" />
			</names>
		</keycode>
		<keycode virtualKeyCode="19"  canOn="false" canOff="false" shortcut="none">
			<names>
				<name value="Pause" />
			</names>
		</keycode>
		<keycode virtualKeyCode="20"  canOn="true" canOff="true" shortcut="none">
			<names>
				<name value="CapsLock" />
				<name value="Capital" />
			</names>
		</keycode>
		<keycode virtualKeyCode="21"  canOn="false" canOff="false" shortcut="none">
			<names>
				<name value="HangulMode" />
				<name value="HanguelMode" />
				<name value="KanaMode" />
			</names>
		</keycode>
		<keycode virtualKeyCode="23"  canOn="false" canOff="false" shortcut="none">
			<names>
				<name value="JunjaMode" />
			</names>
		</keycode>
		<keycode virtualKeyCode="24"  canOn="false" canOff="false" shortcut="none">
			<names>
				<name value="FinalMode" />
			</names>
		</keycode>
		<keycode virtualKeyCode="25"  canOn="false" canOff="false" shortcut="none">
			<names>
				<name value="KanjiMode" />
				<name value="HanjaMode" />
			</names>
		</keycode>
		<keycode virtualKeyCode="27"  canOn="false" canOff="false" shortcut="none">
			<names>
				<name value="Escape" />
			</names>
		</keycode>
		<keycode virtualKeyCode="28"  canOn="false" canOff="false" shortcut="none">
			<names>
				<name value="IMEConvert" />
			</names>
		</keycode>
		<keycode virtualKeyCode="29"  canOn="false" canOff="false" shortcut="none">
			<names>
				<name value="IMENonconvert" />
			</names>
		</keycode>
		<keycode virtualKeyCode="30"  canOn="false" canOff="false" shortcut="none">
			<names>
				<name value="IMEAccept" />
				<name value="IMEAceept" />
			</names>
		</keycode>
		<keycode virtualKeyCode="31"  canOn="false" canOff="false" shortcut="none">
			<names>
				<name value="IMEModeChange" />
			</names>
		</keycode>
		<keycode virtualKeyCode="32"  canOn="false" canOff="false" shortcut="none">
			<names>
				<name value="Space" />
			</names>
		</keycode>
		<keycode virtualKeyCode="33"  canOn="false" canOff="false" shortcut="none">
			<names>
				<name value="PageUp" />
				<name value="Prior" />
			</names>
		</keycode>
		<keycode virtualKeyCode="34"  canOn="false" canOff="false" shortcut="none">
			<names>
				<name value="PageDown" />
				<name value="Next" />
			</names>
		</keycode>
		<keycode virtualKeyCode="35"  canOn="false" canOff="false" shortcut="none">
			<names>
				<name value="End" />
			</names>
		</keycode>
		<keycode virtualKeyCode="36"  canOn="false" canOff="false" shortcut="none">
			<names>
				<name value="Home" />
			</names>
		</keycode>
		<keycode virtualKeyCode="37"  canOn="false" canOff="false" shortcut="none">
			<names>
				<name value="Left" />
			</names>
		</keycode>
		<keycode virtualKeyCode="38"  canOn="false" canOff="false" shortcut="none">
			<names>
				<name value="Up" />
			</names>
		</keycode>
		<keycode virtualKeyCode="39"  canOn="false" canOff="false" shortcut="none">
			<names>
				<name value="Right" />
			</names>
		</keycode>
		<keycode virtualKeyCode="40"  canOn="false" canOff="false" shortcut="none">
			<names>
				<name value="Down" />
			</names>
		</keycode>
		<keycode virtualKeyCode="41"  canOn="false" canOff="false" shortcut="none">
			<names>
				<name value="Select" />
			</names>
		</keycode>
		<keycode virtualKeyCode="42"  canOn="false" canOff="false" shortcut="none">
			<names>
				<name value="Print" />
			</names>
		</keycode>
		<keycode virtualKeyCode="43"  canOn="false" canOff="false" shortcut="none">
			<names>
				<name value="Execute" />
			</names>
		</keycode>
		<keycode virtualKeyCode="44"  canOn="false" canOff="false" shortcut="none">
			<names>
				<name value="PrintScreen" />
				<name value="Snapshot" />
			</names>
		</keycode>
		<keycode virtualKeyCode="45"  canOn="false" canOff="false" shortcut="none">
			<names>
				<name value="Insert" />
			</names>
		</keycode>
		<keycode virtualKeyCode="46"  canOn="false" canOff="false" shortcut="none">
			<names>
				<name value="Delete" />
			</names>
		</keycode>
		<keycode virtualKeyCode="47"  canOn="false" canOff="false" shortcut="none">
			<names>
				<name value="Help" />
			</names>
		</keycode>
		<keycode virtualKeyCode="48"  canOn="false" canOff="false" shortcut="none">
			<names>
				<name value="D0" />
			</names>
		</keycode>
		<keycode virtualKeyCode="49"  canOn="false" canOff="false" shortcut="none">
			<names>
				<name value="D1" />
			</names>
		</keycode>
		<keycode virtualKeyCode="50"  canOn="false" canOff="false" shortcut="none">
			<names>
				<name value="D2" />
			</names>
		</keycode>
		<keycode virtualKeyCode="51"  canOn="false" canOff="false" shortcut="none">
			<names>
				<name value="D3" />
			</names>
		</keycode>
		<keycode virtualKeyCode="52"  canOn="false" canOff="false" shortcut="none">
			<names>
				<name value="D4" />
			</names>
		</keycode>
		<keycode virtualKeyCode="53"  canOn="false" canOff="false" shortcut="none">
			<names>
				<name value="D5" />
			</names>
		</keycode>
		<keycode virtualKeyCode="54"  canOn="false" canOff="false" shortcut="none">
			<names>
				<name value="D6" />
			</names>
		</keycode>
		<keycode virtualKeyCode="55"  canOn="false" canOff="false" shortcut="none">
			<names>
				<name value="D7" />
			</names>
		</keycode>
		<keycode virtualKeyCode="56"  canOn="false" canOff="false" shortcut="none">
			<names>
				<name value="D8" />
			</names>
		</keycode>
		<keycode virtualKeyCode="57"  canOn="false" canOff="false" shortcut="none">
			<names>
				<name value="D9" />
			</names>
		</keycode>
		<keycode virtualKeyCode="65"  canOn="false" canOff="false" shortcut="none">
			<names>
				<name value="A" />
			</names>
		</keycode>
		<keycode virtualKeyCode="66"  canOn="false" canOff="false" shortcut="none">
			<names>
				<name value="B" />
			</names>
		</keycode>
		<keycode virtualKeyCode="67"  canOn="false" canOff="false" shortcut="none">
			<names>
				<name value="C" />
			</names>
		</keycode>
		<keycode virtualKeyCode="68"  canOn="false" canOff="false" shortcut="none">
			<names>
				<name value="D" />
			</names>
		</keycode>
		<keycode virtualKeyCode="69"  canOn="false" canOff="false" shortcut="none">
			<names>
				<name value="E" />
			</names>
		</keycode>
		<keycode virtualKeyCode="70"  canOn="false" canOff="false" shortcut="none">
			<names>
				<name value="F" />
			</names>
		</keycode>
		<keycode virtualKeyCode="71"  canOn="false" canOff="false" shortcut="none">
			<names>
				<name value="G" />
			</names>
		</keycode>
		<keycode virtualKeyCode="72"  canOn="false" canOff="false" shortcut="none">
			<names>
				<name value="H" />
			</names>
		</keycode>
		<keycode virtualKeyCode="73"  canOn="false" canOff="false" shortcut="none">
			<names>
				<name value="I" />
			</names>
		</keycode>
		<keycode virtualKeyCode="74"  canOn="false" canOff="false" shortcut="none">
			<names>
				<name value="J" />
			</names>
		</keycode>
		<keycode virtualKeyCode="75"  canOn="false" canOff="false" shortcut="none">
			<names>
				<name value="K" />
			</names>
		</keycode>
		<keycode virtualKeyCode="76"  canOn="false" canOff="false" shortcut="none">
			<names>
				<name value="L" />
			</names>
		</keycode>
		<keycode virtualKeyCode="77"  canOn="false" canOff="false" shortcut="none">
			<names>
				<name value="M" />
			</names>
		</keycode>
		<keycode virtualKeyCode="78"  canOn="false" canOff="false" shortcut="none">
			<names>
				<name value="N" />
			</names>
		</keycode>
		<keycode virtualKeyCode="79"  canOn="false" canOff="false" shortcut="none">
			<names>
				<name value="O" />
			</names>
		</keycode>
		<keycode virtualKeyCode="80"  canOn="false" canOff="false" shortcut="none">
			<names>
				<name value="P" />
			</names>
		</keycode>
		<keycode virtualKeyCode="81"  canOn="false" canOff="false" shortcut="none">
			<names>
				<name value="Q" />
			</names>
		</keycode>
		<keycode virtualKeyCode="82"  canOn="false" canOff="false" shortcut="none">
			<names>
				<name value="R" />
			</names>
		</keycode>
		<keycode virtualKeyCode="83"  canOn="false" canOff="false" shortcut="none">
			<names>
				<name value="S" />
			</names>
		</keycode>
		<keycode virtualKeyCode="84"  canOn="false" canOff="false" shortcut="none">
			<names>
				<name value="T" />
			</names>
		</keycode>
		<keycode virtualKeyCode="85"  canOn="false" canOff="false" shortcut="none">
			<names>
				<name value="U" />
			</names>
		</keycode>
		<keycode virtualKeyCode="86"  canOn="false" canOff="false" shortcut="none">
			<names>
				<name value="V" />
			</names>
		</keycode>
		<keycode virtualKeyCode="87"  canOn="false" canOff="false" shortcut="none">
			<names>
				<name value="W" />
			</names>
		</keycode>
		<keycode virtualKeyCode="88"  canOn="false" canOff="false" shortcut="none">
			<names>
				<name value="X" />
			</names>
		</keycode>
		<keycode virtualKeyCode="89"  canOn="false" canOff="false" shortcut="none">
			<names>
				<name value="Y" />
			</names>
		</keycode>
		<keycode virtualKeyCode="90"  canOn="false" canOff="false" shortcut="none">
			<names>
				<name value="Z" />
			</names>
		</keycode>
		<keycode virtualKeyCode="91"  canOn="false" canOff="false" shortcut="#">
			<names>
				<name value="LWin" />
			</names>
		</keycode>
		<keycode virtualKeyCode="92"  canOn="false" canOff="false" shortcut="none">
			<names>
				<name value="RWin" />
			</names>
		</keycode>
		<keycode virtualKeyCode="93"  canOn="false" canOff="false" shortcut="none">
			<names>
				<name value="Apps" />
			</names>
		</keycode>
		<keycode virtualKeyCode="95"  canOn="false" canOff="false" shortcut="none">
			<names>
				<name value="Sleep" />
			</names>
		</keycode>
		<keycode virtualKeyCode="96"  canOn="false" canOff="false" shortcut="none">
			<names>
				<name value="NumPad0" />
			</names>
		</keycode>
		<keycode virtualKeyCode="97"  canOn="false" canOff="false" shortcut="none">
			<names>
				<name value="NumPad1" />
			</names>
		</keycode>
		<keycode virtualKeyCode="98"  canOn="false" canOff="false" shortcut="none">
			<names>
				<name value="NumPad2" />
			</names>
		</keycode>
		<keycode virtualKeyCode="99"  canOn="false" canOff="false" shortcut="none">
			<names>
				<name value="NumPad3" />
			</names>
		</keycode>
		<keycode virtualKeyCode="100"  canOn="false" canOff="false" shortcut="none">
			<names>
				<name value="NumPad4" />
			</names>
		</keycode>
		<keycode virtualKeyCode="101"  canOn="false" canOff="false" shortcut="none">
			<names>
				<name value="NumPad5" />
			</names>
		</keycode>
		<keycode virtualKeyCode="102"  canOn="false" canOff="false" shortcut="none">
			<names>
				<name value="NumPad6" />
			</names>
		</keycode>
		<keycode virtualKeyCode="103"  canOn="false" canOff="false" shortcut="none">
			<names>
				<name value="NumPad7" />
			</names>
		</keycode>
		<keycode virtualKeyCode="104"  canOn="false" canOff="false" shortcut="none">
			<names>
				<name value="NumPad8" />
			</names>
		</keycode>
		<keycode virtualKeyCode="105"  canOn="false" canOff="false" shortcut="none">
			<names>
				<name value="NumPad9" />
			</names>
		</keycode>
		<keycode virtualKeyCode="106"  canOn="false" canOff="false" shortcut="none">
			<names>
				<name value="Multiply" />
			</names>
		</keycode>
		<keycode virtualKeyCode="107"  canOn="false" canOff="false" shortcut="none">
			<names>
				<name value="Add" />
			</names>
		</keycode>
		<keycode virtualKeyCode="108"  canOn="false" canOff="false" shortcut="none">
			<names>
				<name value="Separator" />
			</names>
		</keycode>
		<keycode virtualKeyCode="109"  canOn="false" canOff="false" shortcut="none">
			<names>
				<name value="Subtract" />
			</names>
		</keycode>
		<keycode virtualKeyCode="110"  canOn="false" canOff="false" shortcut="none">
			<names>
				<name value="Decimal" />
			</names>
		</keycode>
		<keycode virtualKeyCode="111"  canOn="false" canOff="false" shortcut="none">
			<names>
				<name value="Divide" />
			</names>
		</keycode>
		<keycode virtualKeyCode="112"  canOn="false" canOff="false" shortcut="none">
			<names>
				<name value="F1" />
			</names>
		</keycode>
		<keycode virtualKeyCode="113"  canOn="false" canOff="false" shortcut="none">
			<names>
				<name value="F2" />
			</names>
		</keycode>
		<keycode virtualKeyCode="114"  canOn="false" canOff="false" shortcut="none">
			<names>
				<name value="F3" />
			</names>
		</keycode>
		<keycode virtualKeyCode="115"  canOn="false" canOff="false" shortcut="none">
			<names>
				<name value="F4" />
			</names>
		</keycode>
		<keycode virtualKeyCode="116"  canOn="false" canOff="false" shortcut="none">
			<names>
				<name value="F5" />
			</names>
		</keycode>
		<keycode virtualKeyCode="117"  canOn="false" canOff="false" shortcut="none">
			<names>
				<name value="F6" />
			</names>
		</keycode>
		<keycode virtualKeyCode="118"  canOn="false" canOff="false" shortcut="none">
			<names>
				<name value="F7" />
			</names>
		</keycode>
		<keycode virtualKeyCode="119"  canOn="false" canOff="false" shortcut="none">
			<names>
				<name value="F8" />
			</names>
		</keycode>
		<keycode virtualKeyCode="120"  canOn="false" canOff="false" shortcut="none">
			<names>
				<name value="F9" />
			</names>
		</keycode>
		<keycode virtualKeyCode="121"  canOn="false" canOff="false" shortcut="none">
			<names>
				<name value="F10" />
			</names>
		</keycode>
		<keycode virtualKeyCode="122"  canOn="false" canOff="false" shortcut="none">
			<names>
				<name value="F11" />
			</names>
		</keycode>
		<keycode virtualKeyCode="123"  canOn="false" canOff="false" shortcut="none">
			<names>
				<name value="F12" />
			</names>
		</keycode>
		<keycode virtualKeyCode="124"  canOn="false" canOff="false" shortcut="none">
			<names>
				<name value="F13" />
			</names>
		</keycode>
		<keycode virtualKeyCode="125"  canOn="false" canOff="false" shortcut="none">
			<names>
				<name value="F14" />
			</names>
		</keycode>
		<keycode virtualKeyCode="126"  canOn="false" canOff="false" shortcut="none">
			<names>
				<name value="F15" />
			</names>
		</keycode>
		<keycode virtualKeyCode="127"  canOn="false" canOff="false" shortcut="none">
			<names>
				<name value="F16" />
			</names>
		</keycode>
		<keycode virtualKeyCode="128"  canOn="false" canOff="false" shortcut="none">
			<names>
				<name value="F17" />
			</names>
		</keycode>
		<keycode virtualKeyCode="129"  canOn="false" canOff="false" shortcut="none">
			<names>
				<name value="F18" />
			</names>
		</keycode>
		<keycode virtualKeyCode="130"  canOn="false" canOff="false" shortcut="none">
			<names>
				<name value="F19" />
			</names>
		</keycode>
		<keycode virtualKeyCode="131"  canOn="false" canOff="false" shortcut="none">
			<names>
				<name value="F20" />
			</names>
		</keycode>
		<keycode virtualKeyCode="132"  canOn="false" canOff="false" shortcut="none">
			<names>
				<name value="F21" />
			</names>
		</keycode>
		<keycode virtualKeyCode="133"  canOn="false" canOff="false" shortcut="none">
			<names>
				<name value="F22" />
			</names>
		</keycode>
		<keycode virtualKeyCode="134"  canOn="false" canOff="false" shortcut="none">
			<names>
				<name value="F23" />
			</names>
		</keycode>
		<keycode virtualKeyCode="135"  canOn="false" canOff="false" shortcut="none">
			<names>
				<name value="F24" />
			</names>
		</keycode>
		<keycode virtualKeyCode="144"  canOn="true" canOff="false" shortcut="none">
			<names>
				<name value="NumLock" />
			</names>
		</keycode>
		<keycode virtualKeyCode="145"  canOn="true" canOff="false" shortcut="none">
			<names>
				<name value="Scroll" />
			</names>
		</keycode>
		<keycode virtualKeyCode="160"  canOn="false" canOff="false" shortcut="+">
			<names>
				<name value="LShiftKey" />
			</names>
		</keycode>
		<keycode virtualKeyCode="161"  canOn="false" canOff="false" shortcut="none">
			<names>
				<name value="RShiftKey" />
			</names>
		</keycode>
		<keycode virtualKeyCode="162"  canOn="false" canOff="false" shortcut="^">
			<names>
				<name value="LControlKey" />
			</names>
		</keycode>
		<keycode virtualKeyCode="163"  canOn="false" canOff="false" shortcut="none">
			<names>
				<name value="RControlKey" />
			</names>
		</keycode>
		<keycode virtualKeyCode="164"  canOn="false" canOff="false" shortcut="!">
			<names>
				<name value="LMenu" />
			</names>
		</keycode>
		<keycode virtualKeyCode="165"  canOn="false" canOff="false" shortcut="none">
			<names>
				<name value="RMenu" />
			</names>
		</keycode>
		<keycode virtualKeyCode="166"  canOn="false" canOff="false" shortcut="none">
			<names>
				<name value="BrowserBack" />
			</names>
		</keycode>
		<keycode virtualKeyCode="167"  canOn="false" canOff="false" shortcut="none">
			<names>
				<name value="BrowserForward" />
			</names>
		</keycode>
		<keycode virtualKeyCode="168"  canOn="false" canOff="false" shortcut="none">
			<names>
				<name value="BrowserRefresh" />
			</names>
		</keycode>
		<keycode virtualKeyCode="169"  canOn="false" canOff="false" shortcut="none">
			<names>
				<name value="BrowserStop" />
			</names>
		</keycode>
		<keycode virtualKeyCode="170"  canOn="false" canOff="false" shortcut="none">
			<names>
				<name value="BrowserSearch" />
			</names>
		</keycode>
		<keycode virtualKeyCode="171"  canOn="false" canOff="false" shortcut="none">
			<names>
				<name value="BrowserFavorites" />
			</names>
		</keycode>
		<keycode virtualKeyCode="172"  canOn="false" canOff="false" shortcut="none">
			<names>
				<name value="BrowserHome" />
			</names>
		</keycode>
		<keycode virtualKeyCode="173"  canOn="false" canOff="false" shortcut="none">
			<names>
				<name value="VolumeMute" />
			</names>
		</keycode>
		<keycode virtualKeyCode="174"  canOn="false" canOff="false" shortcut="none">
			<names>
				<name value="VolumeDown" />
			</names>
		</keycode>
		<keycode virtualKeyCode="175"  canOn="false" canOff="false" shortcut="none">
			<names>
				<name value="VolumeUp" />
			</names>
		</keycode>
		<keycode virtualKeyCode="176"  canOn="false" canOff="false" shortcut="none">
			<names>
				<name value="MediaNextTrack" />
			</names>
		</keycode>
		<keycode virtualKeyCode="177"  canOn="false" canOff="false" shortcut="none">
			<names>
				<name value="MediaPreviousTrack" />
			</names>
		</keycode>
		<keycode virtualKeyCode="178"  canOn="false" canOff="false" shortcut="none">
			<names>
				<name value="MediaStop" />
			</names>
		</keycode>
		<keycode virtualKeyCode="179"  canOn="false" canOff="false" shortcut="none">
			<names>
				<name value="MediaPlayPause" />
			</names>
		</keycode>
		<keycode virtualKeyCode="180"  canOn="false" canOff="false" shortcut="none">
			<names>
				<name value="LaunchMail" />
			</names>
		</keycode>
		<keycode virtualKeyCode="181"  canOn="false" canOff="false" shortcut="none">
			<names>
				<name value="SelectMedia" />
			</names>
		</keycode>
		<keycode virtualKeyCode="182"  canOn="false" canOff="false" shortcut="none">
			<names>
				<name value="LaunchApplication1" />
			</names>
		</keycode>
		<keycode virtualKeyCode="183"  canOn="false" canOff="false" shortcut="none">
			<names>
				<name value="LaunchApplication2" />
			</names>
		</keycode>
		<keycode virtualKeyCode="186"  canOn="false" canOff="false" shortcut="none">
			<names>
				<name value="OemSemicolon" />
				<name value="Oem1" />
			</names>
		</keycode>
		<keycode virtualKeyCode="187"  canOn="false" canOff="false" shortcut="none">
			<names>
				<name value="Oemplus" />
			</names>
		</keycode>
		<keycode virtualKeyCode="188"  canOn="false" canOff="false" shortcut="none">
			<names>
				<name value="Oemcomma" />
			</names>
		</keycode>
		<keycode virtualKeyCode="189"  canOn="false" canOff="false" shortcut="none">
			<names>
				<name value="OemMinus" />
			</names>
		</keycode>
		<keycode virtualKeyCode="190"  canOn="false" canOff="false" shortcut="none">
			<names>
				<name value="OemPeriod" />
			</names>
		</keycode>
		<keycode virtualKeyCode="191"  canOn="false" canOff="false" shortcut="none">
			<names>
				<name value="Oem2" />
				<name value="OemQuestion" />
			</names>
		</keycode>
		<keycode virtualKeyCode="192"  canOn="false" canOff="false" shortcut="none">
			<names>
				<name value="Oem3" />
				<name value="Oemtilde" />
			</names>
		</keycode>
		<keycode virtualKeyCode="219"  canOn="false" canOff="false" shortcut="none">
			<names>
				<name value="Oem4" />
				<name value="OemOpenBrackets" />
			</names>
		</keycode>
		<keycode virtualKeyCode="220"  canOn="false" canOff="false" shortcut="none">
			<names>
				<name value="OemPipe" />
				<name value="Oem5" />
			</names>
		</keycode>
		<keycode virtualKeyCode="221"  canOn="false" canOff="false" shortcut="none">
			<names>
				<name value="OemCloseBrackets" />
				<name value="Oem6" />
			</names>
		</keycode>
		<keycode virtualKeyCode="222"  canOn="false" canOff="false" shortcut="none">
			<names>
				<name value="OemQuotes" />
				<name value="Oem7" />
			</names>
		</keycode>
		<keycode virtualKeyCode="223"  canOn="false" canOff="false" shortcut="none">
			<names>
				<name value="Oem8" />
			</names>
		</keycode>
		<keycode virtualKeyCode="226"  canOn="false" canOff="false" shortcut="none">
			<names>
				<name value="Oem102" />
				<name value="OemBackslash" />
			</names>
		</keycode>
		<keycode virtualKeyCode="229"  canOn="false" canOff="false" shortcut="none">
			<names>
				<name value="ProcessKey" />
			</names>
		</keycode>
		<keycode virtualKeyCode="231"  canOn="false" canOff="false" shortcut="none">
			<names>
				<name value="Packet" />
			</names>
		</keycode>
		<keycode virtualKeyCode="246"  canOn="false" canOff="false" shortcut="none">
			<names>
				<name value="Attn" />
			</names>
		</keycode>
		<keycode virtualKeyCode="247"  canOn="false" canOff="false" shortcut="none">
			<names>
				<name value="Crsel" />
			</names>
		</keycode>
		<keycode virtualKeyCode="248"  canOn="false" canOff="false" shortcut="none">
			<names>
				<name value="Exsel" />
			</names>
		</keycode>
		<keycode virtualKeyCode="249"  canOn="false" canOff="false" shortcut="none">
			<names>
				<name value="EraseEof" />
			</names>
		</keycode>
		<keycode virtualKeyCode="250"  canOn="false" canOff="false" shortcut="none">
			<names>
				<name value="Play" />
			</names>
		</keycode>
		<keycode virtualKeyCode="251"  canOn="false" canOff="false" shortcut="none">
			<names>
				<name value="Zoom" />
			</names>
		</keycode>
		<keycode virtualKeyCode="252"  canOn="false" canOff="false" shortcut="none">
			<names>
				<name value="NoName" />
			</names>
		</keycode>
		<keycode virtualKeyCode="253"  canOn="false" canOff="false" shortcut="none">
			<names>
				<name value="Pa1" />
			</names>
		</keycode>
		<keycode virtualKeyCode="254"  canOn="false" canOff="false" shortcut="none">
			<names>
				<name value="OemClear" />
			</names>
		</keycode>
		<keycode virtualKeyCode="65535"  canOn="false" canOff="false" shortcut="none">
			<names>
				<name value="KeyCode" />
			</names>
		</keycode>
		<keycode virtualKeyCode="65536"  canOn="false" canOff="false" shortcut="+">
			<names>
				<name value="Shift" />
			</names>
		</keycode>
		<keycode virtualKeyCode="131072"  canOn="false" canOff="false" shortcut="none">
			<names>
				<name value="Control" />
			</names>
		</keycode>
		<keycode virtualKeyCode="262144"  canOn="false" canOff="false" shortcut="none">
			<names>
				<name value="Alt" />
			</names>
		</keycode>
		<keycode virtualKeyCode="-65536"  canOn="false" canOff="false" shortcut="none">
			<names>
				<name value="Modifiers" />
			</names>
		</keycode>
	</keycodes>
</configuration>